CHANGES.txt
LICENSE
MANIFEST.in
README.rst
requirements.txt
setup.py
protox/__init__.py
protox/bibtex.py
protox/constants.py
protox/objects.py
protox/protocols/__init__.py
protox/protocols/protocol_protox.py
protox/tests/__init__.py
protox/viewers/__init__.py
protox/viewers/viewers_protox.py
scipion_chem_protox.egg-info/PKG-INFO
scipion_chem_protox.egg-info/SOURCES.txt
scipion_chem_protox.egg-info/dependency_links.txt
scipion_chem_protox.egg-info/entry_points.txt
scipion_chem_protox.egg-info/requires.txt
scipion_chem_protox.egg-info/top_level.txt