Metadata-Version: 2.1
Name: scipion-chem-protox
Version: 0.1
Summary: Scipion framework plugin for the use of Protox software tool
Home-page: https://github.com/scipion-chem/scipion-chem-protox
Author: Veronica Gamo
Author-email: veronica.gamoparejo@usp.ceu.es
Keywords: scipion Protox scipion-3.0 cheminformatics
License-File: LICENSE
Requires-Dist: scipion-pyworkflow
Requires-Dist: scipion-em
Requires-Dist: scipion-chem
